Workbook

Sheet README
B2: ACTIVITY PROGRAM
B3: May 2026 - Spring in Bloom
B4: Anchor Care Consulting
B6: May celebrates spring at its peak: gardens bloom, family gathers for Mother's Day, and the country pauses on Memorial Day to remember those who served. Programming this month leans into flowers, picnics, derby fun, patriotic music, berry season, and warm weather socials.
B8: HOW TO USE THIS WORKBOOK
B9: Calendar - May 2026: Visual at-a-glance grid of the whole month. Print landscape on letter paper for the bulletin board.
B10: Daily Activities: The full day-by-day plan: every day's 5 activities (Exercise, Newspaper+Word Game, Afternoon, Supper, Evening) with descriptions, supplies, and level adaptations. This is the planning workhorse.
B11: Bonus Events: The 6 special bigger events for the month - Kentucky Derby Watch Party, Cinco de Mayo Fiesta, Mother's Day Tea, Armed Forces Day, Memorial Day Cookout, Senior Health & Fitness Fair. Each has supply lists.
B12: Holidays: Quick reference: every 'fun' holiday tied to each day so you can plan future months the same way.
B13: Roster: Replace the placeholder names with your actual residents. Names flow into the Charting tab.
B14: Charting: Per-resident attendance and participation tracking. Each resident has a row, every day's 5 activities are columns. Use codes A (active) / O (observed) / D (declined) / N/A (not available). Counters at the bottom auto-tally.
B15: Word Games: Reusable library of word games, anagrams, riddles, and trivia - pull from here when filling future months.
... B28: • SN = Skilled Nursing / Long-Term Care - seated, gentle, often staff-assisted

Sheet Calendar - May 2026
A1: MAY 2026
A2: Spring in Bloom
A3: MONDAY | B3: TUESDAY | C3: WEDNESDAY | D3: THURSDAY | E3: FRIDAY | F3: SATURDAY | G3: SUNDAY
E4: 1 May Day & National Mother Goose Day | F4: 2 Kentucky Derby Day (1st Saturday) | G4: 3 National Garden Meditation Day
E5: AM: Chair Yoga: Spring Awakening News: 'Welcome to May' Word Search PM: May Basket Craft Social Sup: Riddle of the Day Eve: Movie Night: 'Driving Miss Daisy' (1989) | F5: AM: Derby Day Warm-Up News: Sports Headlines + Famous Horses Trivia PM: Make-Your-Own Derby Hat Workshop Sup: Derby Trivia Cards on Tables Eve: Kentucky Derby Watch Party - SEE BONUS EVENT (May 2) | G5: AM: Sunday Stretch & Hymn Hour News: Sunday Comics Read-Aloud + Garden Word List PM: Garden Meditation & Plant Potting Sup: Limerick Read-Aloud (early intro for the 12th) Eve: Hymn Sing-Along + Cards in Lounge
A6: 4 Star Wars Day - 'May the 4th Be With You' | B6: 5 Cinco de Mayo | C6: 6 National Nurses Day & National Beverage Day | D6: 7 National Roast Leg of Lamb Day | E6: 8 V-E Day (Victory in Europe, 1945) & No Socks Day | F6: 9 National Lost Sock Memorial Day & National Train Day | G6: 10 Mother's Day & National Shrimp Day
A7: AM: Star Wars 'Jedi Training' Stretch News: Front-Page News + Movie Trivia PM: Galaxy Trivia & Snack Social Sup: Famous Movie Lines Match-Up Eve: Movie Night: 'Cocoon' (1985) | B7: AM: Salsa Dance Movement (Seated) News: Cinco de Mayo Word Search (Spanish-English) PM: Cinco de Mayo Fiesta - SEE BONUS EVENT Sup: 'Categories' Game at Tables Eve: Group Game: Loteria (Mexican Bingo) | C7: AM: Resistance Band Workout: Strong Like a Nurse News: Newspaper + 'Things My Mom/Nurse Said' Reminiscence PM: Make-a-Card for Local Nursing Staff Sup: Trivia Card: Beverages Around the World Eve: Group Game: Wheel of Fortune (DIY) | D7: AM: Walking Club: Indoor Lap or Garden Stroll News: Garden Section + Flower Crossword (Easy) PM: Bingo! Sup: Riddle: Spring Edition Eve: Movie Night: 'On Golden Pond' (1981) | E7: AM: Dance Movement: Big Band Era News: V-E Day History Read + 1940s Word Search PM: Mother's Day Tea (Pre-Celebration) - SEE BONUS EVENT Sup: Trivia: Decade Match Eve: Sing-Along: 1940s Hit Parade | F7: AM: Marching Band Movement News: Travel Section + Train Trivia PM: Sock Hop & Lost Sock Memorial Sup: Travel Word Game Eve: Movie Night: 'Strangers on a Train' (1951) [Light edit] | G7: AM: Sunday Gentle Stretch + Mom's Favorite Songs News: Sunday Paper + 'Mom's Wisdom' Word List PM: Mother's Day Tea Hour & Family Visiting Sup: Trivia: Famous Mothers in History Eve: Movie Night: 'Steel Magnolias' (1989)
A8: 11 National Eat What You Want Day | B8: 12 International Nurses Day & National Limerick Day | C8: 13 National Apple Pie Day & National Frog Jumping Day | D8: 14 National Buttermilk Biscuit Day | E8: 15 National Chocolate Chip Day | F8: 16 Armed Forces Day (3rd Saturday) & National BBQ Day | G8: 17 National Walnut Day
A9: AM: Standing/Seated Balance Practice News: Food Section + 'Eat What You Want' Vote PM: Card Tournament: Skip-Bo, UNO, Rummy Sup: Riddle Night Eve: Group Game: Pictionary (Senior Edition) | B9: AM: Tai Chi Basics (Seated) News: Limerick Day Special PM: Manicure & Music Social Sup: Limerick at Each Table Eve: Movie Night: 'Driving Miss Daisy' alternative skipped - instead 'Calendar Girls' (2003) | C9: AM: Apple Pie Energizer News: Food Section + Apple Pie Recipe Read-Aloud PM: Apple Pie Tasting + Cooking Demo Sup: Trivia: Famous Pies in Pop Culture Eve: Group Game: Name That Tune (Pie Edition - then general) | D9: AM: Resistance Band: Upper Body Focus News: Food Section + Biscuit Recipe Reminiscence PM: Biscuit + Jam Tasting Social Sup: Categories Game: Southern Food Eve: Movie Night: 'Fried Green Tomatoes' (1991) | E9: AM: Chair Yoga: Shoulder & Neck Relief News: Newspaper + Chocolate Chip Cookie History PM: Cookie Decorating Social Sup: Endangered Species Trivia Eve: Group Game: 'Name the Decade' | F9: AM: Patriotic Marching Movement News: Newspaper + Military Branches Word Match PM: Armed Forces Day Honor Ceremony - SEE BONUS EVENT Sup: Trivia at Tables: Military History Eve: Movie Night: 'The Best Years of Our Lives' (1946) | G9: AM: Sunday Stretch with Soft Hymns News: Sunday Comics + Walnut Trivia PM: Sunday Hymn Sing & Visiting Hour Sup: Riddle: Trees & Fall Eve: Cards & Quiet Time
A10: 18 International Museum Day | B10: 19 National Devil's Food Cake Day | C10: 20 National Pick Strawberries Day | D10: 21 National Memo Day & National Strawberries & Cream Day | E10: 22 National Maritime Day & National Vanilla Pudding Day | F10: 23 National Lucky Penny Day & World Turtle Day | G10: 24 National Scavenger Hunt Day
A11: AM: Walking Club: Museum Walk News: Newspaper + Art Trivia PM: Watercolor Painting Hour Sup: Trivia: Famous Museums Eve: Movie Night: 'The Best Exotic Marigold Hotel' (2011) | B11: AM: Resistance Band: Lower Body Focus News: Food Section + Devil's Food Cake History PM: Cake & Coffee Social Sup: Categories: Things That Are Sweet Eve: Group Game: Charades (Senior Edition) | C11: AM: Strawberry Picking Movement News: Newspaper + Strawberry Recipe Read PM: Strawberry Shortcake Social Sup: Riddle Night Eve: Movie Night: 'Strawberry Shortcake' (animated, family-friendly) - or alt 'Ratatouille' (2007) | D11: AM: Chair Yoga: Hip Openers News: Newspaper + 'Memo to Self' Writing Activity PM: Strawberries & Cream Tea Social Sup: Trivia: Famous Memos in History Eve: Group Game: Bingo with Music Themes | E11: AM: Dance Movement: Big Band & Maritime Songs News: Newspaper + Maritime Day Word Search PM: Vanilla Pudding Sundae Bar Sup: Categories: Things on a Boat Eve: Movie Night: 'Captains Courageous' (1937) or 'Old Man and the Sea' (1958) | F11: AM: Walking Club: Garden + Penny Pickup News: Newspaper + Penny Trivia PM: Turtle Day Slow-and-Steady Trivia Sup: Riddle: Lucky Things Eve: Movie Night: 'Cocoon: The Return' (1988) - alt 'A League of Their Own' (1992) | G11: AM: Sunday Stretch + Quiet Reflection News: Sunday Paper + Scavenger Hunt Word List PM: Indoor Scavenger Hunt + Ice Cream Sup: Categories: 'Things You'd Find in a Scavenger Hunt' Eve: Movie + Card Lounge
A12: 25 MEMORIAL DAY & National Wine Day | B12: 26 National Blueberry Cheesecake Day & National Paper Airplane Day | C12: 27 National Grape Popsicle Day & Sun Screen Day | D12: 28 National Hamburger Day & Senior Health & Fitness Day | E12: 29 JFK's Birthday & National Coq au Vin Day | F12: 30 National Mint Julep Day | G12: 31 National Macaroon Day
A13: AM: Patriotic Movement Hour News: Newspaper + Memorial Day Reading PM: Memorial Day Cookout & Remembrance - SEE BONUS EVENT Sup: Trivia: U.S. Patriotic History Eve: Movie Night: 'Saving Private Ryan' (Light edit) - alt 'The Notebook' (2004) | B13: AM: Resistance Band: Full Body Quick Routine News: Newspaper + Paper Airplane Folding PM: Blueberry Cheesecake Social Sup: Riddle Night Eve: Group Game: Bingo + Music | C13: AM: Chair Yoga: Sun Salutation Adaptation News: Newspaper + Sun & Skin Care Tips PM: Grape Popsicle Outdoor Time Sup: Categories: Summer Things Eve: Movie Night: 'Sandlot' (1993) or 'Field of Dreams' (1989) | D13: AM: Senior Health & Fitness Fair Warm-Up News: Newspaper + Health Tips Trivia PM: Senior Health & Fitness Fair - SEE BONUS EVENT Sup: Trivia: Famous Hamburger Joints Eve: Group Game: Bingo + Burger Bar | E13: AM: Dance Movement: Camelot Era News: Newspaper + JFK Reminiscence Word List PM: Old-Time Sing-Along + Snack Sup: Trivia: 1960s Eve: Movie Night: 'Hidden Figures' (2016) or 'Apollo 13' (1995) | F13: AM: Saturday Morning Country Movement News: Newspaper + Mint Julep Recipe Read PM: Saturday Card Tournament + Mint Lemonade Sup: Riddle Night Eve: Movie Night: 'Seabiscuit' (2003) | G13: AM: Sunday Closing Stretch News: Sunday Comics + 'Goodbye May' Word List PM: Macaroon & Tea Closing Social Sup: Trivia: May in Review Eve: Movie Night (Closing the Month): 'The Sound of Music' (1965)
A15: LEGEND | GOLD = Major Holiday | LIGHT GOLD = Bonus Event Day | BLUE = Weekday | LIGHT BLUE = Weekend

Sheet Daily Activities
A1: Date | B1: Day | C1: Holiday / Theme | D1: Slot | E1: Time | F1: Activity Title | G1: Description, Supplies, Level Adaptations
A2: May 1 | B2: Friday | C2: May Day & National Mother Goose Day | D2: Morning Exercise | E2: 9:30-10:00 AM | F2: Chair Yoga: Spring Awakening | G2: Gentle 25-min seated yoga sequence with a flower-and-garden visualization. Focus on shoulder rolls, neck stretches, hip openers. Bring a fresh flower for each resident to hold during closing breath. AL: standing balance pose option. MC: leader demonstrates each move slowly, repeats cues. SN: passive range-of-motion assistance for those who need it.
A3: May 1 | B3: Friday | C3: May Day & National Mother Goose Day | D3: Newspaper + Word Game | E3: 10:30-11:30 AM | F3: 'Welcome to May' Word Search | G3: Read morning headlines aloud (weather, sports, light human-interest). Distribute the May Day word search (large print on Word Puzzle sheet #1). Words: MAYDAY, FLOWERS, SPRING, BASKET, RIBBON, MAYPOLE, BLOOM, BIRDS, GREEN, WARM. MC: do as a group on a whiteboard with leader pointing.
A4: May 1 | B4: Friday | C4: May Day & National Mother Goose Day | D4: Afternoon Social | E4: 2:00-3:00 PM | F4: May Basket Craft Social | G4: Old tradition: fill paper cones with flowers and hang on neighbors' doors. Residents decorate small paper cones (pre-cut), fill with fresh or silk flowers and a candy. Deliver baskets to staff offices and to residents who couldn't attend. Coffee and cookies served. AL/MC: full participation. SN: pre-assembled cones, resident adds 1-2 decorative touches.
A5: May 1 | B5: Friday | C5: May Day & National Mother Goose Day | D5: Supper Word Puzzle | E5: 5:30-6:30 PM | F5: Riddle of the Day | G5: Place this riddle card at every table: 'I'm tall when I'm young and short when I'm old. What am I?' (Answer: a candle.) Bonus: 'What flower has two lips?' (a tulip). Encourage table conversation.
A6: May 1 | B6: Friday | C6: May Day & National Mother Goose Day | D6: Evening Movie/Game | E6: 6:30-8:00 PM | F6: Movie Night: 'Driving Miss Daisy' (1989) | G6: Beloved classic, PG, 99 min, about friendship across decades. Popcorn and lemonade. Lights low but not off. Provide closed captions. MC alternative: 30-min episode of 'I Love Lucy' season 2 in their lounge.
A7: May 2 | B7: Saturday | C7: Kentucky Derby Day (1st Saturday) | D7: Morning Exercise | E7: 9:30-10:00 AM | F7: Derby Day Warm-Up | G7: Themed energizer: 'horses at the gate' marching in place 1 min, 'reaching for the roses' overhead reach x10, 'galloping arms' alternating reach x20, ankle circles, seated kicks. End with 'Photo finish!' freeze pose. Play 'Camptown Races' as background. ~25 min.
A8: May 2 | B8: Saturday | C8: Kentucky Derby Day (1st Saturday) | D8: Newspaper + Word Game | E8: 10:30-11:30 AM | F8: Sports Headlines + Famous Horses Trivia | G8: Read the day's sports section, especially Derby coverage. Trivia card: name three Triple Crown winners (Secretariat 1973, Affirmed 1978, American Pharoah 2015, Justify 2018). Group word scramble: HORSESHOE, JOCKEY, DERBY, ROSES, BLANKET.
A9: May 2 | B9: Saturday | C9: Kentucky Derby Day (1st Saturday) | D9: Afternoon Social | E9: 2:00-3:00 PM | F9: Make-Your-Own Derby Hat Workshop | G9: Pre-cut paper sun-hats. Bins of ribbons, silk flowers, feathers, and tulle. Glue dots (safer than hot glue) and sticky tape. Music: 'My Old Kentucky Home.' Photograph each resident in their hat for the bulletin board. SN: residents who can't manipulate small items get an aide-assisted hat plus they 'judge' style.
A10: May 2 | B10: Saturday | C10: Kentucky Derby Day (1st Saturday) | D10: Supper Word Puzzle | E10: 5:30-6:30 PM | F10: Derby Trivia Cards on Tables | G10: One question per table: 'What flower wraps the Derby winner?' (red roses), 'How long is the Derby race?' (1.25 miles), 'In what state is Churchill Downs?' (Kentucky). Encourage discussion.
A11: May 2 | B11: Saturday | C11: Kentucky Derby Day (1st Saturday) | D11: Evening Movie/Game | E11: 6:30-8:00 PM | F11: Kentucky Derby Watch Party - SEE BONUS EVENT (May 2) | G11: See the bonus event sheet for full details. 6:00-7:30 PM in main activity room. Residents not attending: cards or quiet movie ('National Velvet,' 1944) in lounge.
A12: May 3 | B12: Sunday | C12: National Garden Meditation Day | D12: Morning Exercise | E12: 9:30-10:00 AM | F12: Sunday Stretch & Hymn Hour | G12: Slow seated stretch sequence to gospel music ('Amazing Grace,' 'How Great Thou Art'). 20 minutes - this is a calmer Sunday pace. Optional Bible reading for those who wish. Ends with deep breathing.
... A156: May 31 | B156: Sunday | C156: National Macaroon Day | D156: Evening Movie/Game | E156: 6:30-8:00 PM | F156: Movie Night (Closing the Month): 'The Sound of Music' (1965) | G156: G, 174 min. May is May - sing-along finale. Show in two parts if needed (but Sunday night is good for the long version). Lyrics on screen if you have a sing-along version. MC: condensed 30-min musical highlights.

Sheet Bonus Events
A1: May 2026 - BONUS MONTHLY EVENTS
A2: Six big planned events scattered through the month - the highlights residents will remember.
A4: Date | B4: Event | C4: Description | D4: Supplies Needed | E4: Lead Staff
A5: May 2 | B5: Kentucky Derby Watch Party | C5: Gather residents in the activity room with a TV tuned to NBC's Derby coverage (post time around 6:45 PM ET). Set up a 'Run for the Roses' theme: red rose centerpieces, paper fancy hats for residents to decorate, mock $1 betting slips (use poker chips, no real wagering), mint juleps (mocktail or alcoholic per facility policy), and a pre-race trivia game about famous Triple Crown winners. Print a list of the entered horses so residents can pick a favorite. MC adaptation: pre-decorated hats; play 'My Old Kentucky Home' on a loop. | D5: TV, paper hats, ribbons/feathers/glue, red roses, mint mocktails, play money, race-day printable
A6: May 5 | B6: Cinco de Mayo Fiesta | C6: Mid-afternoon fiesta with mariachi music playlist, paper flag banners, guacamole-and-chip station (or tortilla pinwheels for soft diets), non-alcoholic agua fresca, and a piñata-style 'tap with a paddle' alternative where residents take turns tapping a hanging crepe-paper container that breaks open easily. Mexican loteria can be played as a Bingo variant - we have a printable card on the Word Game tab. | D6: Mariachi music, decorations, snacks, loteria cards, soft piñata
A7: May 8 | B7: Mother's Day Tea (Pre-celebration) | C7: High tea event timed before Mother's Day so visiting families can attend. Set tables with linen, china teacups, finger sandwiches (cucumber, egg salad), scones with jam, lemon bars. Live or recorded harp / piano music. Honor every female resident as a 'mother figure' regardless of biological motherhood. Hand out fresh flower corsages or boutonnieres. Have a memory book at each table where families and residents can record favorite memories of their own mothers. | D7: Tea service, finger foods, flowers, memory books/pens, soft music
A8: May 16 | B8: Armed Forces Day Honor Ceremony | C8: 30-minute ceremony in the dining room recognizing veteran residents and staff. Display branch flags (Army, Navy, Air Force, Marines, Coast Guard, Space Force). Each veteran resident receives a hand-signed thank-you card prepared by local schoolchildren or staff in advance. Play patriotic music (anthems of each branch). Invite a local color guard or scout troop if available. Serve red, white, and blue cupcakes. Photograph each veteran for the family bulletin board. | D8: Flags, thank-you cards, patriotic playlist, cupcakes, camera
A9: May 25 | B9: Memorial Day Cookout & Remembrance | C9: All-facility outdoor (weather permitting) or activity-room cookout. Hot dogs, hamburgers, potato salad, watermelon, lemonade, and ice cream. Live music if budget allows - otherwise a curated patriotic + 1950s-60s playlist. Brief moment of silence at noon (national tradition). Display photos of veteran residents in uniform. Outdoor games: horseshoes (lightweight rubber), corn-hole, lawn bowling. MC/SN: shaded patio seating, pinwheels and flags to hold, music focus. | D9: Cookout food, beverages, decorations, lawn games, sound system
A10: May 28 | B10: Senior Health & Fitness Fair | C10: Half-day mini-fair with stations residents rotate through: (1) Blood pressure check by nursing staff, (2) Hand-grip strength assessment, (3) Hydration education + flavored water tasting, (4) Brain-game station with crosswords and Sudoku, (5) Chair-yoga demo. Hand out 'Health Champion' ribbons to all participants. | D10: BP cuff, grip dynamometer, water/fruit, puzzles, ribbons

Sheet Holidays
A1: May 2026 HOLIDAYS & FUN DAYS
A3: Date | B3: Day of Week | C3: Holiday / Theme
A4: May 1 | B4: Friday | C4: May Day & National Mother Goose Day
A5: May 2 | B5: Saturday | C5: Kentucky Derby Day (1st Saturday)
A6: May 3 | B6: Sunday | C6: National Garden Meditation Day
A7: May 4 | B7: Monday | C7: Star Wars Day - 'May the 4th Be With You'
A8: May 5 | B8: Tuesday | C8: Cinco de Mayo
A9: May 6 | B9: Wednesday | C9: National Nurses Day & National Beverage Day
A10: May 7 | B10: Thursday | C10: National Roast Leg of Lamb Day
A11: May 8 | B11: Friday | C11: V-E Day (Victory in Europe, 1945) & No Socks Day
A12: May 9 | B12: Saturday | C12: National Lost Sock Memorial Day & National Train Day
A13: May 10 | B13: Sunday | C13: Mother's Day & National Shrimp Day
A14: May 11 | B14: Monday | C14: National Eat What You Want Day
... A34: May 31 | B34: Sunday | C34: National Macaroon Day

Sheet Roster
A1: RESIDENT ROSTER
A2: Replace placeholder names with your actual residents. Names auto-link to the Charting tab.
A4: # | B4: Resident Name | C4: Care Level (AL/MC/SN) | D4: Notes (mobility, hearing, preferences)
A5: 1 | B5: Resident 1
A6: 2 | B6: Resident 2
A7: 3 | B7: Resident 3
A8: 4 | B8: Resident 4
A9: 5 | B9: Resident 5
A10: 6 | B10: Resident 6
A11: 7 | B11: Resident 7
A12: 8 | B12: Resident 8
A13: 9 | B13: Resident 9
A14: 10 | B14: Resident 10
A15: 11 | B15: Resident 11
A16: 12 | B16: Resident 12
... A24: 20 | B24: Resident 20
A25: 21
A26: 22
A27: 23
A28: 24
A29: 25
A30: 26
A31: 27
A32: 28
A33: 29
A34: 30

Sheet Charting
A1: PARTICIPATION CHARTING - May 2026
A2: Codes: A = Active | O = Observed | D = Declined | N/A = Not Available (room/family/ill) | Leave blank = No record yet
A3: RESIDENT | B3: 1 Fri | G3: 2 Sat | L3: 3 Sun | Q3: 4 Mon | V3: 5 Tue | AA3: 6 Wed | AF3: 7 Thu | AK3: 8 Fri | AP3: 9 Sat | AU3: 10 Sun | AZ3: 11 Mon | BE3: 12 Tue | BJ3: 13 Wed | BO3: 14 Thu | BT3: 15 Fri | BY3: 16 Sat | CD3: 17 Sun | CI3: 18 Mon | CN3: 19 Tue | CS3: 20 Wed | CX3: 21 Thu | DC3: 22 Fri | DH3: 23 Sat | DM3: 24 Sun | DR3: 25 Mon | DW3: 26 Tue | EB3: 27 Wed | EG3: 28 Thu | EL3: 29 Fri | EQ3: 30 Sat | EV3: 31 Sun | FA3: Total Active | FB3: Total Observed | FC3: Total Declined | FD3: Total N/A | FE3: Engagement Rate
B4: Ex | C4: Nw | D4: Af | E4: Su | F4: Ev | G4: Ex | H4: Nw | I4: Af | J4: Su | K4: Ev | L4: Ex | M4: Nw | N4: Af | O4: Su | P4: Ev | Q4: Ex | R4: Nw | S4: Af | T4: Su | U4: Ev | V4: Ex | W4: Nw | X4: Af | Y4: Su | Z4: Ev | AA4: Ex | AB4: Nw | AC4: Af | AD4: Su | AE4: Ev | AF4: Ex | AG4: Nw | AH4: Af | AI4: Su | AJ4: Ev | AK4: Ex | AL4: Nw | AM4: Af | AN4: Su | AO4: Ev | AP4: Ex | AQ4: Nw | AR4: Af | AS4: Su | AT4: Ev | AU4: Ex | AV4: Nw | AW4: Af | AX4: Su | AY4: Ev | AZ4: Ex | BA4: Nw | BB4: Af | BC4: Su | BD4: Ev | BE4: Ex | BF4: Nw | BG4: Af | BH4: Su | BI4: Ev | BJ4: Ex | BK4: Nw | BL4: Af | BM4: Su | BN4: Ev | BO4: Ex | BP4: Nw | BQ4: Af | BR4: Su | BS4: Ev | BT4: Ex | BU4: Nw | BV4: Af | BW4: Su | BX4: Ev | BY4: Ex | BZ4: Nw | CA4: Af | CB4: Su | CC4: Ev | CD4: Ex | CE4: Nw | CF4: Af | CG4: Su | CH4: Ev | CI4: Ex | CJ4: Nw | CK4: Af | CL4: Su | CM4: Ev | CN4: Ex | CO4: Nw | CP4: Af | CQ4: Su | CR4: Ev | CS4: Ex | CT4: Nw | CU4: Af | CV4: Su | CW4: Ev | CX4: Ex | CY4: Nw | CZ4: Af | DA4: Su | DB4: Ev | DC4: Ex | DD4: Nw | DE4: Af | DF4: Su | DG4: Ev | DH4: Ex | DI4: Nw | DJ4: Af | DK4: Su | DL4: Ev | DM4: Ex | DN4: Nw | DO4: Af | DP4: Su | DQ4: Ev | DR4: Ex | DS4: Nw | DT4: Af | DU4: Su | DV4: Ev | DW4: Ex | DX4: Nw | DY4: Af | DZ4: Su | EA4: Ev | EB4: Ex | EC4: Nw | ED4: Af | EE4: Su | EF4: Ev | EG4: Ex | EH4: Nw | EI4: Af | EJ4: Su | EK4: Ev | EL4: Ex | EM4: Nw | EN4: Af | EO4: Su | EP4: Ev | EQ4: Ex | ER4: Nw | ES4: Af | ET4: Su | EU4: Ev | EV4: Ex | EW4: Nw | EX4: Af | EY4: Su | EZ4: Ev
A5: =Roster!B5 -> Resident 1 | FA5: =COUNTIF(B5:EZ5,"A") -> 0 | FB5: =COUNTIF(B5:EZ5,"O") -> 0 | FC5: =COUNTIF(B5:EZ5,"D") -> 0 | FD5: =COUNTIF(B5:EZ5,"N/A") -> 0 | FE5: =IFERROR((FA5+FB5)/(FA5+FB5+FC5),0) -> 0
A6: =Roster!B6 -> Resident 2 | FA6: =COUNTIF(B6:EZ6,"A") -> 0 | FB6: =COUNTIF(B6:EZ6,"O") -> 0 | FC6: =COUNTIF(B6:EZ6,"D") -> 0 | FD6: =COUNTIF(B6:EZ6,"N/A") -> 0 | FE6: =IFERROR((FA6+FB6)/(FA6+FB6+FC6),0) -> 0
A7: =Roster!B7 -> Resident 3 | FA7: =COUNTIF(B7:EZ7,"A") -> 0 | FB7: =COUNTIF(B7:EZ7,"O") -> 0 | FC7: =COUNTIF(B7:EZ7,"D") -> 0 | FD7: =COUNTIF(B7:EZ7,"N/A") -> 0 | FE7: =IFERROR((FA7+FB7)/(FA7+FB7+FC7),0) -> 0
A8: =Roster!B8 -> Resident 4 | FA8: =COUNTIF(B8:EZ8,"A") -> 0 | FB8: =COUNTIF(B8:EZ8,"O") -> 0 | FC8: =COUNTIF(B8:EZ8,"D") -> 0 | FD8: =COUNTIF(B8:EZ8,"N/A") -> 0 | FE8: =IFERROR((FA8+FB8)/(FA8+FB8+FC8),0) -> 0
A9: =Roster!B9 -> Resident 5 | FA9: =COUNTIF(B9:EZ9,"A") -> 0 | FB9: =COUNTIF(B9:EZ9,"O") -> 0 | FC9: =COUNTIF(B9:EZ9,"D") -> 0 | FD9: =COUNTIF(B9:EZ9,"N/A") -> 0 | FE9: =IFERROR((FA9+FB9)/(FA9+FB9+FC9),0) -> 0
A10: =Roster!B10 -> Resident 6 | FA10: =COUNTIF(B10:EZ10,"A") -> 0 | FB10: =COUNTIF(B10:EZ10,"O") -> 0 | FC10: =COUNTIF(B10:EZ10,"D") -> 0 | FD10: =COUNTIF(B10:EZ10,"N/A") -> 0 | FE10: =IFERROR((FA10+FB10)/(FA10+FB10+FC10),0) -> 0
A11: =Roster!B11 -> Resident 7 | FA11: =COUNTIF(B11:EZ11,"A") -> 0 | FB11: =COUNTIF(B11:EZ11,"O") -> 0 | FC11: =COUNTIF(B11:EZ11,"D") -> 0 | FD11: =COUNTIF(B11:EZ11,"N/A") -> 0 | FE11: =IFERROR((FA11+FB11)/(FA11+FB11+FC11),0) -> 0
A12: =Roster!B12 -> Resident 8 | FA12: =COUNTIF(B12:EZ12,"A") -> 0 | FB12: =COUNTIF(B12:EZ12,"O") -> 0 | FC12: =COUNTIF(B12:EZ12,"D") -> 0 | FD12: =COUNTIF(B12:EZ12,"N/A") -> 0 | FE12: =IFERROR((FA12+FB12)/(FA12+FB12+FC12),0) -> 0
A13: =Roster!B13 -> Resident 9 | FA13: =COUNTIF(B13:EZ13,"A") -> 0 | FB13: =COUNTIF(B13:EZ13,"O") -> 0 | FC13: =COUNTIF(B13:EZ13,"D") -> 0 | FD13: =COUNTIF(B13:EZ13,"N/A") -> 0 | FE13: =IFERROR((FA13+FB13)/(FA13+FB13+FC13),0) -> 0
A14: =Roster!B14 -> Resident 10 | FA14: =COUNTIF(B14:EZ14,"A") -> 0 | FB14: =COUNTIF(B14:EZ14,"O") -> 0 | FC14: =COUNTIF(B14:EZ14,"D") -> 0 | FD14: =COUNTIF(B14:EZ14,"N/A") -> 0 | FE14: =IFERROR((FA14+FB14)/(FA14+FB14+FC14),0) -> 0
A15: =Roster!B15 -> Resident 11 | FA15: =COUNTIF(B15:EZ15,"A") -> 0 | FB15: =COUNTIF(B15:EZ15,"O") -> 0 | FC15: =COUNTIF(B15:EZ15,"D") -> 0 | FD15: =COUNTIF(B15:EZ15,"N/A") -> 0 | FE15: =IFERROR((FA15+FB15)/(FA15+FB15+FC15),0) -> 0
A16: =Roster!B16 -> Resident 12 | FA16: =COUNTIF(B16:EZ16,"A") -> 0 | FB16: =COUNTIF(B16:EZ16,"O") -> 0 | FC16: =COUNTIF(B16:EZ16,"D") -> 0 | FD16: =COUNTIF(B16:EZ16,"N/A") -> 0 | FE16: =IFERROR((FA16+FB16)/(FA16+FB16+FC16),0) -> 0
... A34: =Roster!B34 -> 0 | FA34: =COUNTIF(B34:EZ34,"A") -> 0 | FB34: =COUNTIF(B34:EZ34,"O") -> 0 | FC34: =COUNTIF(B34:EZ34,"D") -> 0 | FD34: =COUNTIF(B34:EZ34,"N/A") -> 0 | FE34: =IFERROR((FA34+FB34)/(FA34+FB34+FC34),0) -> 0
A36: ACTIVITY TOTALS (Active count) | B36: =COUNTIF(B5:B34,"A") -> 0 | C36: =COUNTIF(C5:C34,"A") -> 0 | D36: =COUNTIF(D5:D34,"A") -> 0 | E36: =COUNTIF(E5:E34,"A") -> 0 | F36: =COUNTIF(F5:F34,"A") -> 0 | G36: =COUNTIF(G5:G34,"A") -> 0 | H36: =COUNTIF(H5:H34,"A") -> 0 | I36: =COUNTIF(I5:I34,"A") -> 0 | ... EZ36: =COUNTIF(EZ5:EZ34,"A") -> 0

Sheet Word Games
A1: WORD GAME LIBRARY (Reusable)
A2: Pull from these for newspaper word games and supper puzzles. Mix-and-match across days.
A4: Game / Puzzle Type | B4: Words / Theme | C4: Best Used When...
A5: Word Search - Spring | B5: BLOOM, BUD, RAIN, SUN, SOIL, SEED, GROW, GREEN, TULIP, ROSE | C5: Spring/garden mornings
A6: Word Search - Mother's Day | B6: MOM, LOVE, KIND, HUG, HOME, CARE, HEART, FAMILY | C6: Mother's Day week
A7: Word Search - Memorial Day | B7: FLAG, HONOR, BRAVE, STARS, STRIPES, POPPY, VETERAN, FREEDOM | C7: Memorial Day week
A8: Word Search - May Foods | B8: STRAWBERRY, PIE, BISCUIT, COOKIE, COFFEE, TEA, CAKE, JAM | C8: Food-themed days (any day)
A9: Anagram - May Words | B9: MAYDAY, FLOWERS, GARDEN, SUNNY, SPRING, WARM, BLOOM, FRESH | C9: May-themed warm-up
A10: Crossword - Easy May Themes | B10: 9-12 word grid - flowers, holidays, weather | C10: Quiet days, focused thinkers
A11: Riddles - Spring | B11: Various - see daily plan for examples | C11: Light moments, supper or social
A12: Categories - 5 letters | B12: S/M/C/B/T are easiest letters | C12: Group icebreaker, easy fun
A13: Limerick Fill-Ins | B13: First line provided, group rhymes | C13: May 12 (Limerick Day) or any silly day
A14: Famous Sayings Match | B14: Match 'an apple a day...' to 'keeps the doctor away' | C14: Reminiscence circles

Sheet Movies & Games
A1: MOVIE & GROUP GAME LIBRARY
A2: Senior-appropriate movies (with ratings + runtimes) and group games. Spring-themed picks emphasized.
A4: MOVIES (Spring & Year-Round Favorites)
A5: Title (Year) | B5: Rating / Runtime | C5: Why It Works | D5: Notes
A6: Driving Miss Daisy (1989) | B6: PG, 99 min | C6: Friendship across decades
A7: On Golden Pond (1981) | B7: PG, 109 min | C7: Aging couple at a summer cabin
A8: Fried Green Tomatoes (1991) | B8: PG-13, 130 min | C8: Southern friendship
A9: Steel Magnolias (1989) | B9: PG, 117 min | C9: Mother-daughter classic
A10: Cocoon (1985) | B10: PG-13, 117 min | C10: Seniors at a Florida home
A11: The Best Exotic Marigold Hotel (2011) | B11: PG-13, 124 min | C11: British seniors in India
A12: The Notebook (2004) | B12: PG-13, 123 min | C12: Love story spanning decades
A13: A League of Their Own (1992) | B13: PG, 128 min | C13: Women's WWII baseball
A14: Field of Dreams (1989) | B14: PG, 107 min | C14: Baseball + nostalgia
A15: Calendar Girls (2003) | B15: PG-13, 108 min | C15: British charity calendar
A16: Seabiscuit (2003) | B16: PG-13, 140 min | C16: Depression-era racehorse
A17: The Sound of Music (1965) | B17: G, 174 min | C17: Musical sing-along
... A21: It's a Wonderful Life (1946) | B21: G, 130 min | C21: Anytime classic
A24: GROUP GAMES (Reusable Library)
A25: Game | B25: How It Works / Setup
A26: Bingo | B26: Standard senior favorite - large print cards required
A27: Pictionary (Senior Edition) | B27: Whiteboard, large markers, easy clue cards
A28: Charades | B28: Senior-friendly clue list (chores, actors, animals)
A29: Wheel of Fortune (DIY) | B29: Whiteboard version - run by activity director
A30: Name That Tune | B30: 5-second clips, team scoring
A31: Loteria (Mexican Bingo) | B31: Picture cards instead of numbers
A32: Categories | B32: Letter from a hat, 4 categories per round
A33: Trivia (decade-themed) | B33: By era - 40s, 50s, 60s, 70s, 80s
A34: Music Bingo | B34: Cards with song titles instead of numbers
A35: Card Tournament | B35: Skip-Bo, UNO, Rummy, Bridge - multiple tables
A36: Word Scramble | B36: Themed (food, holidays, names)
... A39: Reminiscence Circle | B39: Decade props passed around, share memories
